rethinkmodel/__init__.py
rethinkmodel/db.py
rethinkmodel/manage.py
rethinkmodel/model.py
rethinkmodel-0.1.1.dist-info/LICENSE
rethinkmodel-0.1.1.dist-info/METADATA
rethinkmodel-0.1.1.dist-info/WHEEL
rethinkmodel-0.1.1.dist-info/top_level.txt
rethinkmodel-0.1.1.dist-info/RECORD
