Metadata-Version: 2.1
Name: rethinkmodel
Version: 0.1.1
Summary: ORM to manage RethinkDB database objects
Home-page: https://metal3d.github.io/rethinkmodel/
Author: Patrice Ferlet, France <metal3d@gmail.com>
Author-email: "Patrice Ferlet" <metal3d@gmail.com>
License: MIT License
Project-URL: GitHub, https://github.com/metal3d/rethinkmodel
Project-URL: Bug Tracker, https://github.com/metal3d/rethinkmodel/issues
Keywords: rethinkmodel,rethinkdb,ORM
Platform: UNKNOWN
Classifier: License :: OSI Approved :: MIT License
Classifier: Topic :: Database
Classifier: Programming Language :: Python :: 3.8
Classifier: Programming Language :: Python :: 3.9
Classifier: Typing :: Typed
Requires-Dist: rethinkdb
